diaparser/__init__.py
diaparser/catalog/__init__.py
diaparser/catalog/catalog.py
diaparser/cmds/__init__.py
diaparser/cmds/biaffine_dependency.py
diaparser/cmds/cmd.py
diaparser/models/__init__.py
diaparser/models/dependency.py
diaparser/modules/__init__.py
diaparser/modules/affine.py
diaparser/modules/bert.py
diaparser/modules/char_lstm.py
diaparser/modules/dropout.py
diaparser/modules/lstm.py
diaparser/modules/matrix_tree_theorem.py
diaparser/modules/mlp.py
diaparser/modules/scalar_mix.py
diaparser/parsers/__init__.py
diaparser/parsers/biaffine_dependency.py
diaparser/parsers/parser.py
diaparser/utils/__init__.py
diaparser/utils/alg.py
diaparser/utils/common.py
diaparser/utils/config.py
diaparser/utils/corpus.py
diaparser/utils/data.py
diaparser/utils/embedding.py
diaparser/utils/field.py
diaparser/utils/fn.py
diaparser/utils/logging.py
diaparser/utils/metric.py
diaparser/utils/parallel.py
diaparser/utils/transform.py
diaparser/utils/vocab.py
elg/__init__.py
elg/service.py
elg/wsgi.py
tests/__init__.py
tests/test_alg.py
tests/test_parse.py
tests/test_tokenizer.py
tests/test_transform.py
tokenizer/__init__.py
tokenizer/tokenizer.py
diaparser-1.1.3.dist-info/LICENSE
diaparser-1.1.3.dist-info/METADATA
diaparser-1.1.3.dist-info/WHEEL
diaparser-1.1.3.dist-info/entry_points.txt
diaparser-1.1.3.dist-info/top_level.txt
diaparser-1.1.3.dist-info/RECORD
