Metadata-Version: 2.1
Name: diaparser
Version: 1.1.3
Summary: Direct Attentive Dependency Parser
Home-page: https://github.com/Unipisa/diaparser
Author: Yu Zhang, Giuseppe Attardi
Author-email: yzhang.cs@outlook.com, attardi@di.unipi.it
License: UNKNOWN
Platform: UNKNOWN
Classifier: Programming Language :: Python :: 3
Classifier: License :: OSI Approved :: MIT License
Classifier: Operating System :: OS Independent
Classifier: Topic :: Scientific/Engineering :: Artificial Intelligence
Classifier: Topic :: Text Processing :: Linguistic
Requires-Python: >=3.6
Requires-Dist: torch (>=1.6)
Requires-Dist: transformers
Requires-Dist: nltk
Requires-Dist: stanza (==1.2.3)
Requires-Dist: numpy
